MANIFEST.in
README.md
setup.py
simple_kNN/__init__.py
simple_kNN/distanceMetrics.py
simple_kNN/kFoldCV.py
simple_kNN/kNNClassifier.py
simple_kNN/version.py
simple_kNN.egg-info/PKG-INFO
simple_kNN.egg-info/SOURCES.txt
simple_kNN.egg-info/dependency_links.txt
simple_kNN.egg-info/not-zip-safe
simple_kNN.egg-info/requires.txt
simple_kNN.egg-info/top_level.txt
simple_kNN/datasets/__init__.py
simple_kNN/datasets/_base.py
simple_kNN/datasets/_samples_generator.py
simple_kNN/datasets/data/breast_cancer.csv
simple_kNN/datasets/data/digits.csv.gz
simple_kNN/datasets/data/iris.csv
simple_kNN/datasets/data/wine_data.csv
simple_kNN/datasets/descr/breast_cancer.rst
simple_kNN/datasets/descr/digits.rst
simple_kNN/datasets/descr/iris.rst
simple_kNN/datasets/descr/wine_data.rst