Metadata-Version: 2.1
Name: simple-kNN
Version: 1.1.5
Summary: Simple kNN algorithm with k-Fold Cross Validation
Home-page: https://github.com/chaitanyakasaraneni/simple-kNN
Author: Chaitanya Krishna Kasaraneni
Author-email: kc.kasaraneni@gmail.com
License: UNKNOWN
Platform: UNKNOWN
Classifier: License :: OSI Approved :: MIT License
Classifier: Operating System :: OS Independent
Classifier: Programming Language :: Python :: 3
Classifier: Programming Language :: Python :: 3.6
Classifier: Intended Audience :: Science/Research
Requires-Python: >=3.6
